fishbones/__init__.py
fishbones/decompiler_builtins/__init__.py
fishbones/decompiler_builtins/ghidra.py
fishbones/decompiler_builtins/ida.py
fishbones/endian.py
fishbones/exceptions.py
fishbones/integer.py
fishbones/py.typed
fishbones/virtual_pointer.py
fishbones-0.3.1.dist-info/LICENSE
fishbones-0.3.1.dist-info/WHEEL
fishbones-0.3.1.dist-info/METADATA
fishbones-0.3.1.dist-info/RECORD
